mocap_pose_2d/ViTPose/__init__.py
mocap_pose_2d/ViTPose/configs/_base_/datasets/300w.py
mocap_pose_2d/ViTPose/configs/_base_/datasets/aflw.py
mocap_pose_2d/ViTPose/configs/_base_/datasets/aic.py
mocap_pose_2d/ViTPose/configs/_base_/datasets/aic_info.py
mocap_pose_2d/ViTPose/configs/_base_/datasets/animalpose.py
mocap_pose_2d/ViTPose/configs/_base_/datasets/ap10k.py
mocap_pose_2d/ViTPose/configs/_base_/datasets/ap10k_info.py
mocap_pose_2d/ViTPose/configs/_base_/datasets/atrw.py
mocap_pose_2d/ViTPose/configs/_base_/datasets/coco.py
mocap_pose_2d/ViTPose/configs/_base_/datasets/coco_wholebody.py
mocap_pose_2d/ViTPose/configs/_base_/datasets/coco_wholebody_face.py
mocap_pose_2d/ViTPose/configs/_base_/datasets/coco_wholebody_hand.py
mocap_pose_2d/ViTPose/configs/_base_/datasets/coco_wholebody_info.py
mocap_pose_2d/ViTPose/configs/_base_/datasets/cofw.py
mocap_pose_2d/ViTPose/configs/_base_/datasets/crowdpose.py
mocap_pose_2d/ViTPose/configs/_base_/datasets/deepfashion_full.py
mocap_pose_2d/ViTPose/configs/_base_/datasets/deepfashion_lower.py
mocap_pose_2d/ViTPose/configs/_base_/datasets/deepfashion_upper.py
mocap_pose_2d/ViTPose/configs/_base_/datasets/fly.py
mocap_pose_2d/ViTPose/configs/_base_/datasets/freihand2d.py
mocap_pose_2d/ViTPose/configs/_base_/datasets/h36m.py
mocap_pose_2d/ViTPose/configs/_base_/datasets/halpe.py
mocap_pose_2d/ViTPose/configs/_base_/datasets/horse10.py
mocap_pose_2d/ViTPose/configs/_base_/datasets/interhand2d.py
mocap_pose_2d/ViTPose/configs/_base_/datasets/interhand3d.py
mocap_pose_2d/ViTPose/configs/_base_/datasets/jhmdb.py
mocap_pose_2d/ViTPose/configs/_base_/datasets/locust.py
mocap_pose_2d/ViTPose/configs/_base_/datasets/macaque.py
mocap_pose_2d/ViTPose/configs/_base_/datasets/mhp.py
mocap_pose_2d/ViTPose/configs/_base_/datasets/moveai29.py
mocap_pose_2d/ViTPose/configs/_base_/datasets/moveai35.py
mocap_pose_2d/ViTPose/configs/_base_/datasets/mpi_inf_3dhp.py
mocap_pose_2d/ViTPose/configs/_base_/datasets/mpii.py
mocap_pose_2d-2.3.2.dist-info/METADATA
mocap_pose_2d-2.3.2.dist-info/WHEEL
mocap_pose_2d-2.3.2.dist-info/RECORD
