Metadata-Version: 2.1
Name: mocap-pose-2d
Version: 2.3.2
Summary: 
Keywords: MotionOps,Moveai
Author: move.ai
Author-email: info@move.ai
Requires-Python: >=3.10,<4.0
Classifier: Programming Language :: Python :: 3
Classifier: Programming Language :: Python :: 3.10
Classifier: Programming Language :: Python :: 3.11
Classifier: Programming Language :: Python :: 3.12
Requires-Dist: json-tricks (>=3.17.1,<4.0.0)
Requires-Dist: mmcv-full (==1.7.1)
Requires-Dist: mocap-base (>=2.0.1,<3.0.0)
Requires-Dist: mocap_settings (>=1.6.9,<2.0.0)
Requires-Dist: munkres (>=1.1.4,<2.0.0)
Requires-Dist: timm (>=0.9.2,<0.10.0)
Requires-Dist: torch (==1.13.0)
Requires-Dist: xtcocotools (==1.13)
Requires-Dist: yolov5 (==6.2.0)
